docs-chat-bot/__init__.py
docs-chat-bot/index.py
docs-chat-bot/plugin.py
docs-chat-bot/query.py
docs-chat-bot/js/chat-dialog-plugin.css
docs-chat-bot/js/chat-dialog-plugin.js
docs_chat_bot/__init__.py
docs_chat_bot/docs_chat_bot_server.py
docs_chat_bot/index.py
docs_chat_bot/indexing.py
docs_chat_bot/log.py
docs_chat_bot/plugin.py
docs_chat_bot/query.py
docs_chat_bot/js/chat-dialog-plugin.css
docs_chat_bot/js/chat-dialog-plugin.js
docs_chat_bot-0.0.1.dist-info/LICENSE
docs_chat_bot-0.0.1.dist-info/METADATA
docs_chat_bot-0.0.1.dist-info/WHEEL
docs_chat_bot-0.0.1.dist-info/entry_points.txt
docs_chat_bot-0.0.1.dist-info/top_level.txt
docs_chat_bot-0.0.1.dist-info/RECORD
