Metadata-Version: 2.1
Name: docs-chat-bot
Version: 0.0.1
Summary: docs chat bot by leveraging CHATGPT
Home-page: https://github.com/learnforpractice/docs-chat-bot
Author: learnforpractice
Author-email: learnforpractice@gmail.com
License: MIT
Keywords: mkdocs plugin
Classifier: Operating System :: OS Independent
Classifier: Programming Language :: Python
Classifier: Programming Language :: Python :: 3
Classifier: Programming Language :: Python :: 3.7
Classifier: Programming Language :: Python :: 3.8
Classifier: Programming Language :: Python :: 3.9
Classifier: Programming Language :: Python :: 3.10
Classifier: License :: OSI Approved :: MIT License
Requires-Python: >=3.6
License-File: LICENSE
Requires-Dist: mkdocs (>=1.1)
Requires-Dist: pymdown-extensions (>=9.2)
